snakerunner/__init__.py
snakerunner/listviews.py
snakerunner/pstatsadapter.py
snakerunner/pstatsloader.py
snakerunner/snakerunner.py
snakerunner/squaremap.py
snakerunner/version.py
snakerunner/resources/__init__.py
snakerunner/resources/rsricon_png.py
snakerunner-2.1.0.dist-info/LICENSE
snakerunner-2.1.0.dist-info/METADATA
snakerunner-2.1.0.dist-info/WHEEL
snakerunner-2.1.0.dist-info/entry_points.txt
snakerunner-2.1.0.dist-info/top_level.txt
snakerunner-2.1.0.dist-info/RECORD
