Metadata-Version: 2.1
Name: snakerunner
Version: 2.1.0
Summary: GUI Viewer for Python profiling runs
Home-page: https://github.com/venthur/snakerunner
Author: Bastian Venthur
Author-email: venthur@debian.org
License: BSD
Keywords: profile,gui,wxPython,squaremap
Classifier: License :: OSI Approved :: BSD License
Classifier: Programming Language :: Python
Classifier: Topic :: Software Development :: Libraries :: Python Modules
Classifier: Intended Audience :: Developers
License-File: LICENSE
Requires-Dist: wxpython
